{
    
    "id": 102863753,
    "name": "Walmart No Verified",
    "author": "WWAlberto",
    "creators": ["WWAlberto"],
    "verifier": "elchamcham3",
    "verification": "https://www.youtube.com/watch?v=iF6WVq0x_Cc",
    "percentToQualify": 100,
    "refreshRates": "any",
    "song-title": "Love Nwantiti",
    "records": [
        {    "user": "SkySpeech",
            "link": "https://www.youtube.com/watch?v=9tscMurdh7o",
            "percent": 100,
            "hz": 60
        },
        {    "user": "AntonliraGD",
            "link": "https://www.youtube.com/watch?v=dFBtKbqPsgw",
            "percent": 100,
            "hz": 240
        }
    ]
}
